{
  "procedure.title": "Regressione Lineare Ridge",
  "procedure.description": "Si adatta a L2 o ai modelli di regressione lineare regolarizzati tramite la classe Python sklearn.linear_model.Ridge per una variabile dipendente su una o più variabili indipendenti, e include le modalità opzionali per visualizzare i grafici di traccia e per selezionare il valore dell'iperparametro alfa basato sulla convalida incrociata.",
  "best_model_summary": "Riepilogo del modello migliore",
  "trace_results": "Risultati di Ridge traccia",
  "model_summary": "Riepilogo del modello",
  "dependent_variable": "Variabile dipendente: {0}",
  "model": "Modello: {0}",
  "alpha": "Alfa",
  "statistics": "Statistiche",
  "training_r2": "Addestramento R-quadrato",
  "holdout_r2": "Holdout R-quadrato",
  "regression_coefficients": "Coefficienti regressione Ridge",
  "standardizing_values": "Standardizzazione dei valori",
  "mean": "Media",
  "std_dev": "Dev std.",
  "intercept": "Intercetta",
  "standardized_coefficients": "Coefficienti standardizzati",
  "unstandardized_coefficients": "Coefficienti non standardizzati",
  "footnotes_1": "Valori utilizzati per standardizzare i predittori per la stima. La variabile dipendente non è standardizzata.",
  "footnotes_2": "Intercept non è penalizzata durante la stima.",
  "number_of_crossvalidation_folds": "Numero di ricorrenze con convalida incrociata",
  "model_comparisons": "Confronti dei modelli",
  "average_test_subset_r2": "R-quadrato sottoinsieme di test medio",
  "average_test_subset_mse": "MSE sottoinsieme di test medio",
  "average_test_set_r2": "R-quadrato sottoinsieme di test medio",
  "average_test_set_mse": "MSE sottoinsieme di test medio",
  "nfolds_with_n": "Numero di occorrenze con convalida incrociata: {0}",
  "fold_r2": "R-quadrato occorrenza {0}",
  "fold_mse": "Ricorrenza {0} MSE",
  "dependent_by_predicted_value": "Grafico a dispersione di {0} in base al valore previsto",
  "residual_by_predicted_value": "Grafico a dispersione del residuo in base al valore previsto",
  "predicted_value": "Valore previsto",
  "residual": "Residuo",
  "regression_line_chart_title": "Coefficienti regressione Ridge vs. Alpha",
  "mse_line_chart_title": "MSE vs. Alfa",
  "r2_line_chart_title": "R-quadrato vs. Alfa",
  "average_mse_line_chart_title": "MSE di convalida incrociata media vs. Alfa",
  "average_r2_line_chart_title": "R Square di convalida incrociata media vs. Alfa",
  "predictor_coefficients": "Coefficienti di previsione",
  "mse": "MSE",
  "r2": "R-quadrato",
  "average_mse": "MSE medio",
  "average_r2": "R quadrato medio",
  "training_data": "Per i dati di addestramento.",
  "holdout_data": "Per i dati di holdout.",
  "bottom_footnote_1": "I predittori sono standardizzati. La variabile dipendente rimane nella metrica originale.",
  "bottom_footnote_2": "I predittori e la variabile dipendente rimangono nelle loro metriche originali.",
  "python_returned_msg": "Python ha restituito il seguente messaggio:",
  "python_output": "Output Python",
  "factor_or_covariate.desc": "Selezionare almeno un fattore o covariata",
  "one_alpha_for_fit.desc": "Solo un valore alfa è consentito quando MODE è FIT",
  "footnote_holdout": "Per i dati di holdout",
  "footnote_training": "Per i dati di formazione",
  "alpha_value_error.desc": "I valori alfa devono essere positivi quando la metrica è Lineare"
}